fsr_tools/__init__.py
fsr_tools/fsr.py
fsr_tools-1.0.0.dist-info/LICENSE.md
fsr_tools-1.0.0.dist-info/METADATA
fsr_tools-1.0.0.dist-info/WHEEL
fsr_tools-1.0.0.dist-info/RECORD
