Metadata-Version: 2.3
Name: fsr-tools
Version: 1.0.0
Summary: Linear Feedback Shift Registers in pure Python3
License: MIT
Author: Anubhav Mattoo
Author-email: anubhavmattoo@outlook.com
Requires-Python: >=3.8,<4.0
Classifier: Development Status :: 5 - Production/Stable
Classifier: Intended Audience :: Developers
Classifier: License :: OSI Approved :: MIT License
Classifier: Operating System :: OS Independent
Classifier: Programming Language :: Python :: 3
Classifier: Programming Language :: Python :: 3.8
Classifier: Programming Language :: Python :: 3.9
Classifier: Programming Language :: Python :: 3.10
Classifier: Programming Language :: Python :: 3.11
Classifier: Programming Language :: Python :: 3.12
Classifier: Programming Language :: Python :: 3.13
Classifier: Topic :: Communications
Classifier: Topic :: Internet
Classifier: Topic :: Security :: Cryptography
Project-URL: Bug Tracker, https://github.com/anubhav-narayan/fsr-tools/issues
Project-URL: Homepage, https://github.com/anubhav-narayan/fsr-tools
Project-URL: Repository, https://github.com/anubhav-narayan/fsr-tools
